workfl/__init__.py
workfl-19.6.15.0.dist-info/LICENSE
workfl-19.6.15.0.dist-info/METADATA
workfl-19.6.15.0.dist-info/WHEEL
workfl-19.6.15.0.dist-info/top_level.txt
workfl-19.6.15.0.dist-info/RECORD
