Metadata-Version: 2.1
Name: workfl
Version: 19.6.15.0
Summary: A lightweight markup language for simple workflow diagrams.
Home-page: https://github.com/Dullage/workfl
Author: Adam Dullage
Author-email: adam@dullage.com
License: MIT
Platform: UNKNOWN
